{
  "important_information": {
    "user_id": "12345",
    "Date_of_birth": "04-23-1990",
    "first_name": "Testing",
    "last_name": "LastTest",
    "email": "personEmail@example.com",
    "street_address": "44 Random Street",
    "social_security_number": "##%5-442-%$@!",
    "primary_physician": "Dr.Jane Carter",
    "primary_health_company": "Healthcare Company Name",
    "last_medical_visit": "2023-10-01T12:00:00Z",
    "preferred_language": "English"
  },

"data": [
    { "entry_id": 1, "data_field": "Sample data 1", "long_string": "Lorem ipsum dolor sit amet, consectetur adipiscing elit. Curabitur lacinia.", "timestamp": "2023-10-01T12:01:00Z" },
    { "entry_id": 2, "data_field": "Sample data 2", "long_string": "Lorem ipsum dolor sit amet, consectetur adipiscing elit. Curabitur lacinia.", "timestamp": "2023-10-01T12:02:00Z" },
    { "entry_id": 3, "data_field": "Sample data 3", "long_string": "Lorem ipsum dolor sit amet, consectetur adipiscing elit. Curabitur lacinia.", "timestamp": "2023-10-01T12:03:00Z" },